edgedriver_autoinstaller/__init__.py
edgedriver_autoinstaller/utils.py
edgedriver_autoinstaller-0.2.1.dist-info/LICENSE
edgedriver_autoinstaller-0.2.1.dist-info/METADATA
edgedriver_autoinstaller-0.2.1.dist-info/WHEEL
edgedriver_autoinstaller-0.2.1.dist-info/entry_points.txt
edgedriver_autoinstaller-0.2.1.dist-info/top_level.txt
edgedriver_autoinstaller-0.2.1.dist-info/RECORD
