Metadata-Version: 2.1
Name: edgedriver-autoinstaller
Version: 0.2.1
Summary: Automatically install edgedriver that supports the currently installed version of edge.
Home-page: https://github.com/fc-dev/python-edgedriver-autoinstaller
Author: Federico Capece
Author-email: capece.1744999@studenti.uniroma1.it
License: MIT
Keywords: edgedriver edge selenium splinter
Platform: UNKNOWN
Classifier: Development Status :: 5 - Production/Stable
Classifier: Topic :: Software Development :: Testing
Classifier: Topic :: System :: Installation/Setup
Classifier: Topic :: Software Development :: Libraries :: Python Modules
Classifier: License :: OSI Approved :: MIT License
Classifier: Programming Language :: Python :: 3
Classifier: Programming Language :: Python :: 3.2
Classifier: Programming Language :: Python :: 3.3
Classifier: Programming Language :: Python :: 3.4
Classifier: Programming Language :: Python :: 3.5
Classifier: Programming Language :: Python :: 3.6
Classifier: Programming Language :: Python :: 3.7
Classifier: Programming Language :: Python :: 3.8
Requires-Python: >=3
